AUTHORS.md
MANIFEST.in
README.md
setup.py
licenses/names.txt
prenoms/__init__.py
prenoms/main.py
prenoms/utils.py
prenoms.egg-info/PKG-INFO
prenoms.egg-info/SOURCES.txt
prenoms.egg-info/dependency_links.txt
prenoms.egg-info/entry_points.txt
prenoms.egg-info/top_level.txt
prenoms/data/dist.1891.txt
prenoms/data/dist.1901.txt
prenoms/data/dist.1911.txt
prenoms/data/dist.1921.txt
prenoms/data/dist.1931.txt
prenoms/data/dist.1941.txt
prenoms/data/dist.1951.txt
prenoms/data/dist.1961.txt
prenoms/data/dist.1971.txt
prenoms/data/dist.1981.txt
prenoms/data/dist.1991.txt
prenoms/data/dist.all.txt
prenoms/data/dist.prenoms.f.1901.txt
prenoms/data/dist.prenoms.f.1911.txt
prenoms/data/dist.prenoms.f.1921.txt
prenoms/data/dist.prenoms.f.1931.txt
prenoms/data/dist.prenoms.f.1941.txt
prenoms/data/dist.prenoms.f.1951.txt
prenoms/data/dist.prenoms.f.1961.txt
prenoms/data/dist.prenoms.f.1971.txt
prenoms/data/dist.prenoms.f.1981.txt
prenoms/data/dist.prenoms.f.1991.txt
prenoms/data/dist.prenoms.f.2001.txt
prenoms/data/dist.prenoms.f.2011.txt
prenoms/data/dist.prenoms.f.all.txt
prenoms/data/dist.prenoms.m.1901.txt
prenoms/data/dist.prenoms.m.1911.txt
prenoms/data/dist.prenoms.m.1921.txt
prenoms/data/dist.prenoms.m.1931.txt
prenoms/data/dist.prenoms.m.1941.txt
prenoms/data/dist.prenoms.m.1951.txt
prenoms/data/dist.prenoms.m.1961.txt
prenoms/data/dist.prenoms.m.1971.txt
prenoms/data/dist.prenoms.m.1981.txt
prenoms/data/dist.prenoms.m.1991.txt
prenoms/data/dist.prenoms.m.2001.txt
prenoms/data/dist.prenoms.m.2011.txt
prenoms/data/dist.prenoms.m.all.txt