Metadata-Version: 2.1
Name: prenoms
Version: 0.5.1
Summary: Générateur de noms aléatoire
Home-page: https://github.com/cnovel/prenoms
Author: Cyril Novel
Author-email: pypi-prenoms@kosmon.fr
License: MIT
Platform: UNKNOWN
Classifier: Development Status :: 4 - Beta
Classifier: Environment :: Console
Classifier: License :: OSI Approved :: MIT License
Classifier: Operating System :: OS Independent
Classifier: Programming Language :: Python
Classifier: Programming Language :: Python :: 3.4
Classifier: Programming Language :: Python :: 3.5
Classifier: Programming Language :: Python :: 3.6
Classifier: Programming Language :: Python :: 3.7
Classifier: Programming Language :: Python :: 3.8
